pyio_effect/__init__.py
pyio_effect/core.py
pyio_effect-0.1.4.dist-info/licenses/LICENSE
pyio_effect-0.1.4.dist-info/METADATA
pyio_effect-0.1.4.dist-info/WHEEL
pyio_effect-0.1.4.dist-info/top_level.txt
pyio_effect-0.1.4.dist-info/RECORD
