Metadata-Version: 2.4
Name: pyio-effect
Version: 0.1.4
Summary: Tiny IO/Try-like effect wrapper for Python.
Author: Pablo Picouto Garcia
License: Copyright (c) 2025 Pablo
Project-URL: Homepage, https://github.com/politrons/Dive-into-Python
Project-URL: Issues, https://github.com/politrons/Dive-into-Python
Keywords: effects,monads,io,try,functional
Classifier: Programming Language :: Python :: 3
Classifier: License :: OSI Approved :: MIT License
Classifier: Typing :: Typed
Requires-Python: >=3.9
License-File: LICENSE
Dynamic: license-file
